llm_performance_benchmark/__init__.py
llm_performance_benchmark/llm_performance_benchmark.py
llm_performance_benchmark-1.0.1.dist-info/LICENSE
llm_performance_benchmark-1.0.1.dist-info/METADATA
llm_performance_benchmark-1.0.1.dist-info/WHEEL
llm_performance_benchmark-1.0.1.dist-info/top_level.txt
llm_performance_benchmark-1.0.1.dist-info/RECORD
