Metadata-Version: 2.1
Name: llm_performance_benchmark
Version: 1.0.1
Summary: Benchmark the performance (output speed, latency) of OpenAI compatible endpoints
Home-page: https://github.com/ArtificialAnalysis/LLM_Performance_Benchmark
Author: Artificial Analysis
Author-email: hello@artificialanalysis.ai
Classifier: Programming Language :: Python :: 3
Classifier: License :: OSI Approved :: MIT License
Classifier: Operating System :: OS Independent
Requires-Python: >=3.7.1
License-File: LICENSE
Requires-Dist: openai >=1.14.1
Requires-Dist: tiktoken >=0.6.0
Requires-Dist: requests >=2.25.1
Requires-Dist: urllib3 >=1.26.5
Requires-Dist: charset-normalizer >=2.0.0
